darca_vector_db/__init__.py
darca_vector_db/__version__.py
darca_vector_db/db_client.py
darca_vector_db-0.1.0.dist-info/LICENSE
darca_vector_db-0.1.0.dist-info/METADATA
darca_vector_db-0.1.0.dist-info/WHEEL
darca_vector_db-0.1.0.dist-info/RECORD
